Metadata-Version: 2.1
Name: capturebaudrate
Version: 0.0.3
Summary: A very basic capture
Home-page: UNKNOWN
Author: Ao Zhang
Author-email: aozhang2022@gmail.com
License: MIT
Keywords: calculator
Platform: UNKNOWN
Classifier: Development Status :: 5 - Production/Stable
Classifier: Intended Audience :: Developers
Classifier: Operating System :: MacOS
Classifier: License :: OSI Approved :: MIT License
Classifier: Programming Language :: Python
License-File: LICENCE
